{
	"id": "80eed939-1613-470a-be0b-efccab153e89",
	"name": "PassengerTesting",
	"values": [
		{
			"key": "id",
			"value": "7",
			"type": "default",
			"enabled": true
		},
		{
			"key": "email",
			"value": "mehedyhasanpro007@gmail.com\n",
			"type": "default",
			"enabled": true
		},
		{
			"key": "firstName",
			"value": "Ariya",
			"type": "default",
			"enabled": true
		},
		{
			"key": "lastName",
			"value": "Stark",
			"type": "default",
			"enabled": true
		},
		{
			"key": "base_url",
			"value": " http://localhost:8000",
			"type": "default",
			"enabled": true
		}
	],
	"_postman_variable_scope": "environment",
	"_postman_exported_at": "2023-03-29T18:18:23.303Z",
	"_postman_exported_using": "Postman/9.18.3"
}